hello_pkg/__init__.py
hello_pkg/core.py
hello_pkg_ykp-0.1.0.dist-info/METADATA
hello_pkg_ykp-0.1.0.dist-info/WHEEL
hello_pkg_ykp-0.1.0.dist-info/top_level.txt
hello_pkg_ykp-0.1.0.dist-info/RECORD
