Metadata-Version: 2.4
Name: hello-pkg-ykp
Version: 0.1.0
Summary: A tiny hello world package
Author-email: Your Name <you@example.com>
License: MIT
Project-URL: Homepage, https://github.com/yourname/hello-pkg
Project-URL: Repository, https://github.com/yourname/hello-pkg
Keywords: hello,example
Classifier: Programming Language :: Python :: 3
Classifier: License :: OSI Approved :: MIT License
Classifier: Operating System :: OS Independent
Requires-Python: >=3.8
